ampy/__init__.py
ampy/animation.py
ampy/processing.py
ampy/statistics2d.py
ampy/statistics3d.py
ampy/utils.py
ampy-0.1.3.5.dist-info/WHEEL
ampy-0.1.3.5.dist-info/METADATA
ampy-0.1.3.5.dist-info/RECORD
