Metadata-Version: 2.1
Name: ampy
Version: 0.1.3.5
Summary: Python-based Processing Tool for Active Matter Experiments
Keywords: active-matter,disordered-systems,swarm-robotics,order-parameter,correlation-map
Author-email: Vadim Porvatov <eighonet@gmail.com>, Mikhail Buzakov <m.k.buzakov@gmail.com>
Requires-Python: >=3.8
Classifier: License :: OSI Approved :: GNU General Public License v3 (GPLv3)
Classifier: Programming Language :: Python
Classifier: Programming Language :: Python :: 3.8
Classifier: Programming Language :: Python :: 3.9
Classifier: Programming Language :: Python :: 3.10
Classifier: Programming Language :: Python :: 3.11
Classifier: Programming Language :: Python :: 3 :: Only
Requires-Dist: numpy<=1.21.6
Requires-Dist: matplotlib>=3.7.1
Requires-Dist: ffmpeg-python>=0.2.0
Requires-Dist: opencv-contrib-python==4.6.0.66
Requires-Dist: imageio-ffmpeg>=0.4.8
Requires-Dist: imutils>=0.5.4
Requires-Dist: celluloid>=0.2.0
Requires-Dist: imageio>=2.27.0
Project-URL: documentation, https://ampy.readthedocs.io
Project-URL: homepage, https://swarmtronics.com
Project-URL: repository, https://github.com/swarmtronics/AMPy.git
